Workbook

Sheet Инструкция
A1: Инструкция
A2: 1. Скопируйте ОСВ из 1С и вставьте на лист OSV с ячейки A1.
A3: 2. Не удаляйте служебные колонки J:Q на листе OSV.
A4: 3. P_l и BS считаются по правилам на листах Map_PL и Map_BS.
A5: 4. Если Excel не пересчитал формулы, нажмите F9.
A6: 5. Для себестоимости включен счет 20. Если нужен 90.02*, измените Активно в Map_PL.

Sheet ОСВ
A1: Счет, Наименование счета | B1: Сальдо нач. Дт | C1: Сальдо нач. Кт | D1: Оборот Дт | E1: Оборот Кт | F1: Сальдо кон. Дт | G1: Сальдо кон. Кт | I1: Служебно | J1: Счет | K1: Использовать | L1: Нач.Дт | M1: Нач.Кт | N1: ОборотДт | O1: ОборотКт | P1: Кон.Дт | Q1: Кон.Кт
J2: =IF($A2<>"",LEFT($A2,FIND(",",$A2&",")-1),"") | K2: =IF($J2<>"",1,0) -> 0 | L2: =IF($J2="",0,IF(ISNUMBER($B2),$B2,0)) -> 0 | M2: =IF($J2="",0,IF(ISNUMBER($C2),$C2,0)) -> 0 | N2: =IF($J2="",0,IF(ISNUMBER($D2),$D2,0)) -> 0 | O2: =IF($J2="",0,IF(ISNUMBER($E2),$E2,0)) -> 0 | P2: =IF($J2="",0,IF(ISNUMBER($F2),$F2,0)) -> 0 | Q2: =IF($J2="",0,IF(ISNUMBER($G2),$G2,0)) -> 0
J3: =IF($A3<>"",LEFT($A3,FIND(",",$A3&",")-1),"") | K3: =IF($J3<>"",1,0) -> 0 | L3: =IF($J3="",0,IF(ISNUMBER($B3),$B3,0)) -> 0 | M3: =IF($J3="",0,IF(ISNUMBER($C3),$C3,0)) -> 0 | N3: =IF($J3="",0,IF(ISNUMBER($D3),$D3,0)) -> 0 | O3: =IF($J3="",0,IF(ISNUMBER($E3),$E3,0)) -> 0 | P3: =IF($J3="",0,IF(ISNUMBER($F3),$F3,0)) -> 0 | Q3: =IF($J3="",0,IF(ISNUMBER($G3),$G3,0)) -> 0
J4: =IF($A4<>"",LEFT($A4,FIND(",",$A4&",")-1),"") | K4: =IF($J4<>"",1,0) -> 0 | L4: =IF($J4="",0,IF(ISNUMBER($B4),$B4,0)) -> 0 | M4: =IF($J4="",0,IF(ISNUMBER($C4),$C4,0)) -> 0 | N4: =IF($J4="",0,IF(ISNUMBER($D4),$D4,0)) -> 0 | O4: =IF($J4="",0,IF(ISNUMBER($E4),$E4,0)) -> 0 | P4: =IF($J4="",0,IF(ISNUMBER($F4),$F4,0)) -> 0 | Q4: =IF($J4="",0,IF(ISNUMBER($G4),$G4,0)) -> 0
J5: =IF($A5<>"",LEFT($A5,FIND(",",$A5&",")-1),"") | K5: =IF($J5<>"",1,0) -> 0 | L5: =IF($J5="",0,IF(ISNUMBER($B5),$B5,0)) -> 0 | M5: =IF($J5="",0,IF(ISNUMBER($C5),$C5,0)) -> 0 | N5: =IF($J5="",0,IF(ISNUMBER($D5),$D5,0)) -> 0 | O5: =IF($J5="",0,IF(ISNUMBER($E5),$E5,0)) -> 0 | P5: =IF($J5="",0,IF(ISNUMBER($F5),$F5,0)) -> 0 | Q5: =IF($J5="",0,IF(ISNUMBER($G5),$G5,0)) -> 0
J6: =IF($A6<>"",LEFT($A6,FIND(",",$A6&",")-1),"") | K6: =IF($J6<>"",1,0) -> 0 | L6: =IF($J6="",0,IF(ISNUMBER($B6),$B6,0)) -> 0 | M6: =IF($J6="",0,IF(ISNUMBER($C6),$C6,0)) -> 0 | N6: =IF($J6="",0,IF(ISNUMBER($D6),$D6,0)) -> 0 | O6: =IF($J6="",0,IF(ISNUMBER($E6),$E6,0)) -> 0 | P6: =IF($J6="",0,IF(ISNUMBER($F6),$F6,0)) -> 0 | Q6: =IF($J6="",0,IF(ISNUMBER($G6),$G6,0)) -> 0
J7: =IF($A7<>"",LEFT($A7,FIND(",",$A7&",")-1),"") | K7: =IF($J7<>"",1,0) -> 0 | L7: =IF($J7="",0,IF(ISNUMBER($B7),$B7,0)) -> 0 | M7: =IF($J7="",0,IF(ISNUMBER($C7),$C7,0)) -> 0 | N7: =IF($J7="",0,IF(ISNUMBER($D7),$D7,0)) -> 0 | O7: =IF($J7="",0,IF(ISNUMBER($E7),$E7,0)) -> 0 | P7: =IF($J7="",0,IF(ISNUMBER($F7),$F7,0)) -> 0 | Q7: =IF($J7="",0,IF(ISNUMBER($G7),$G7,0)) -> 0
J8: =IF($A8<>"",LEFT($A8,FIND(",",$A8&",")-1),"") | K8: =IF($J8<>"",1,0) -> 0 | L8: =IF($J8="",0,IF(ISNUMBER($B8),$B8,0)) -> 0 | M8: =IF($J8="",0,IF(ISNUMBER($C8),$C8,0)) -> 0 | N8: =IF($J8="",0,IF(ISNUMBER($D8),$D8,0)) -> 0 | O8: =IF($J8="",0,IF(ISNUMBER($E8),$E8,0)) -> 0 | P8: =IF($J8="",0,IF(ISNUMBER($F8),$F8,0)) -> 0 | Q8: =IF($J8="",0,IF(ISNUMBER($G8),$G8,0)) -> 0
J9: =IF($A9<>"",LEFT($A9,FIND(",",$A9&",")-1),"") | K9: =IF($J9<>"",1,0) -> 0 | L9: =IF($J9="",0,IF(ISNUMBER($B9),$B9,0)) -> 0 | M9: =IF($J9="",0,IF(ISNUMBER($C9),$C9,0)) -> 0 | N9: =IF($J9="",0,IF(ISNUMBER($D9),$D9,0)) -> 0 | O9: =IF($J9="",0,IF(ISNUMBER($E9),$E9,0)) -> 0 | P9: =IF($J9="",0,IF(ISNUMBER($F9),$F9,0)) -> 0 | Q9: =IF($J9="",0,IF(ISNUMBER($G9),$G9,0)) -> 0
J10: =IF($A10<>"",LEFT($A10,FIND(",",$A10&",")-1),"") | K10: =IF($J10<>"",1,0) -> 0 | L10: =IF($J10="",0,IF(ISNUMBER($B10),$B10,0)) -> 0 | M10: =IF($J10="",0,IF(ISNUMBER($C10),$C10,0)) -> 0 | N10: =IF($J10="",0,IF(ISNUMBER($D10),$D10,0)) -> 0 | O10: =IF($J10="",0,IF(ISNUMBER($E10),$E10,0)) -> 0 | P10: =IF($J10="",0,IF(ISNUMBER($F10),$F10,0)) -> 0 | Q10: =IF($J10="",0,IF(ISNUMBER($G10),$G10,0)) -> 0
J11: =IF($A11<>"",LEFT($A11,FIND(",",$A11&",")-1),"") | K11: =IF($J11<>"",1,0) -> 0 | L11: =IF($J11="",0,IF(ISNUMBER($B11),$B11,0)) -> 0 | M11: =IF($J11="",0,IF(ISNUMBER($C11),$C11,0)) -> 0 | N11: =IF($J11="",0,IF(ISNUMBER($D11),$D11,0)) -> 0 | O11: =IF($J11="",0,IF(ISNUMBER($E11),$E11,0)) -> 0 | P11: =IF($J11="",0,IF(ISNUMBER($F11),$F11,0)) -> 0 | Q11: =IF($J11="",0,IF(ISNUMBER($G11),$G11,0)) -> 0
J12: =IF($A12<>"",LEFT($A12,FIND(",",$A12&",")-1),"") | K12: =IF($J12<>"",1,0) -> 0 | L12: =IF($J12="",0,IF(ISNUMBER($B12),$B12,0)) -> 0 | M12: =IF($J12="",0,IF(ISNUMBER($C12),$C12,0)) -> 0 | N12: =IF($J12="",0,IF(ISNUMBER($D12),$D12,0)) -> 0 | O12: =IF($J12="",0,IF(ISNUMBER($E12),$E12,0)) -> 0 | P12: =IF($J12="",0,IF(ISNUMBER($F12),$F12,0)) -> 0 | Q12: =IF($J12="",0,IF(ISNUMBER($G12),$G12,0)) -> 0
J13: =IF($A13<>"",LEFT($A13,FIND(",",$A13&",")-1),"") | K13: =IF($J13<>"",1,0) -> 0 | L13: =IF($J13="",0,IF(ISNUMBER($B13),$B13,0)) -> 0 | M13: =IF($J13="",0,IF(ISNUMBER($C13),$C13,0)) -> 0 | N13: =IF($J13="",0,IF(ISNUMBER($D13),$D13,0)) -> 0 | O13: =IF($J13="",0,IF(ISNUMBER($E13),$E13,0)) -> 0 | P13: =IF($J13="",0,IF(ISNUMBER($F13),$F13,0)) -> 0 | Q13: =IF($J13="",0,IF(ISNUMBER($G13),$G13,0)) -> 0
... J5000: =IF($A5000<>"",LEFT($A5000,FIND(",",$A5000&",")-1),"") | K5000: =IF($J5000<>"",1,0) -> 0 | L5000: =IF($J5000="",0,IF(ISNUMBER($B5000),$B5000,0)) -> 0 | M5000: =IF($J5000="",0,IF(ISNUMBER($C5000),$C5000,0)) -> 0 | N5000: =IF($J5000="",0,IF(ISNUMBER($D5000),$D5000,0)) -> 0 | O5000: =IF($J5000="",0,IF(ISNUMBER($E5000),$E5000,0)) -> 0 | P5000: =IF($J5000="",0,IF(ISNUMBER($F5000),$F5000,0)) -> 0 | Q5000: =IF($J5000="",0,IF(ISNUMBER($G5000),$G5000,0)) -> 0

Sheet Маппинг_PL
A1: Активно
A2: Статья
A3: Счет mask
A4: Источник
A5: Знак
A6: Сумма
A7: 1 | B7: Выручка | C7: 90.01 | D7: ОборотКт | E7: 1 | F7: =IF($A7<>1,0,$E7*IF($D7="ОборотДт",SUMIFS(ОСВ!$N$2:$N$5000,ОСВ!$J$2:$J$5000,$C7,ОСВ!$K$2:$K$5000,1),IF($D7="ОборотКт",SUMIFS(ОСВ!$O$2:$O$5000,ОСВ!$J$2:$J$5000,$C7,ОСВ!$K$2:$K$5000,1),0))) -> 0
A8: 1 | B8: Выручка | C8: 90.03 | D8: ОборотДт | E8: -1 | F8: =IF($A8<>1,0,$E8*IF($D8="ОборотДт",SUMIFS(ОСВ!$N$2:$N$5000,ОСВ!$J$2:$J$5000,$C8,ОСВ!$K$2:$K$5000,1),IF($D8="ОборотКт",SUMIFS(ОСВ!$O$2:$O$5000,ОСВ!$J$2:$J$5000,$C8,ОСВ!$K$2:$K$5000,1),0))) -> 0
A9: 1 | B9: Себестоимость | C9: 20 | D9: ОборотДт | E9: -1 | F9: =IF($A9<>1,0,$E9*IF($D9="ОборотДт",SUMIFS(ОСВ!$N$2:$N$5000,ОСВ!$J$2:$J$5000,$C9,ОСВ!$K$2:$K$5000,1),IF($D9="ОборотКт",SUMIFS(ОСВ!$O$2:$O$5000,ОСВ!$J$2:$J$5000,$C9,ОСВ!$K$2:$K$5000,1),0))) -> 0
A10: 0 | B10: Себестоимость | C10: 90.02 | D10: ОборотДт | E10: -1 | F10: =IF($A10<>1,0,$E10*IF($D10="ОборотДт",SUMIFS(ОСВ!$N$2:$N$5000,ОСВ!$J$2:$J$5000,$C10,ОСВ!$K$2:$K$5000,1),IF($D10="ОборотКт",SUMIFS(ОСВ!$O$2:$O$5000,ОСВ!$J$2:$J$5000,$C10,ОСВ!$K$2:$K$5000,1),0))) -> 0
A11: 1 | B11: Коммерческие расходы | C11: 44 | D11: ОборотДт | E11: -1 | F11: =IF($A11<>1,0,$E11*IF($D11="ОборотДт",SUMIFS(ОСВ!$N$2:$N$5000,ОСВ!$J$2:$J$5000,$C11,ОСВ!$K$2:$K$5000,1),IF($D11="ОборотКт",SUMIFS(ОСВ!$O$2:$O$5000,ОСВ!$J$2:$J$5000,$C11,ОСВ!$K$2:$K$5000,1),0))) -> 0
A12: 1 | B12: Общехозяйственные расходы | C12: 26 | D12: ОборотДт | E12: -1 | F12: =IF($A12<>1,0,$E12*IF($D12="ОборотДт",SUMIFS(ОСВ!$N$2:$N$5000,ОСВ!$J$2:$J$5000,$C12,ОСВ!$K$2:$K$5000,1),IF($D12="ОборотКт",SUMIFS(ОСВ!$O$2:$O$5000,ОСВ!$J$2:$J$5000,$C12,ОСВ!$K$2:$K$5000,1),0))) -> 0
A13: 1 | B13: Прочие доходы | C13: 91.01 | D13: ОборотКт | E13: 1 | F13: =IF($A13<>1,0,$E13*IF($D13="ОборотДт",SUMIFS(ОСВ!$N$2:$N$5000,ОСВ!$J$2:$J$5000,$C13,ОСВ!$K$2:$K$5000,1),IF($D13="ОборотКт",SUMIFS(ОСВ!$O$2:$O$5000,ОСВ!$J$2:$J$5000,$C13,ОСВ!$K$2:$K$5000,1),0))) -> 0
A14: 1 | B14: Прочие расходы | C14: 91.02 | D14: ОборотДт | E14: -1 | F14: =IF($A14<>1,0,$E14*IF($D14="ОборотДт",SUMIFS(ОСВ!$N$2:$N$5000,ОСВ!$J$2:$J$5000,$C14,ОСВ!$K$2:$K$5000,1),IF($D14="ОборотКт",SUMIFS(ОСВ!$O$2:$O$5000,ОСВ!$J$2:$J$5000,$C14,ОСВ!$K$2:$K$5000,1),0))) -> 0
A15: 1 | B15: Налог на прибыль | C15: 68.04 | D15: ОборотКт | E15: -1 | F15: =IF($A15<>1,0,$E15*IF($D15="ОборотДт",SUMIFS(ОСВ!$N$2:$N$5000,ОСВ!$J$2:$J$5000,$C15,ОСВ!$K$2:$K$5000,1),IF($D15="ОборотКт",SUMIFS(ОСВ!$O$2:$O$5000,ОСВ!$J$2:$J$5000,$C15,ОСВ!$K$2:$K$5000,1),0))) -> 0

Sheet Маппинг_BS
A1: Активно
A2: Статья
A3: Счет mask
A4: Сторона
A5: Знак
A6: Начало
A7: Конец
A8: 1 | B8: Деньги | C8: 50 | D8: Дт | E8: 1 | F8: =IF($A8<>1,0,$E8*IF($D8="Дт",SUMIFS(ОСВ!$L$2:$L$5000,ОСВ!$J$2:$J$5000,$C8,ОСВ!$K$2:$K$5000,1),SUMIFS(ОСВ!$M$2:$M$5000,ОСВ!$J$2:$J$5000,$C8,ОСВ!$K$2:$K$5000,1))) -> 0 | G8: =IF($A8<>1,0,$E8*IF($D8="Дт",SUMIFS(ОСВ!$P$2:$P$5000,ОСВ!$J$2:$J$5000,$C8,ОСВ!$K$2:$K$5000,1),SUMIFS(ОСВ!$Q$2:$Q$5000,ОСВ!$J$2:$J$5000,$C8,ОСВ!$K$2:$K$5000,1))) -> 0
A9: 1 | B9: Деньги | C9: 51 | D9: Дт | E9: 1 | F9: =IF($A9<>1,0,$E9*IF($D9="Дт",SUMIFS(ОСВ!$L$2:$L$5000,ОСВ!$J$2:$J$5000,$C9,ОСВ!$K$2:$K$5000,1),SUMIFS(ОСВ!$M$2:$M$5000,ОСВ!$J$2:$J$5000,$C9,ОСВ!$K$2:$K$5000,1))) -> 0 | G9: =IF($A9<>1,0,$E9*IF($D9="Дт",SUMIFS(ОСВ!$P$2:$P$5000,ОСВ!$J$2:$J$5000,$C9,ОСВ!$K$2:$K$5000,1),SUMIFS(ОСВ!$Q$2:$Q$5000,ОСВ!$J$2:$J$5000,$C9,ОСВ!$K$2:$K$5000,1))) -> 0
A10: 1 | B10: Деньги | C10: 52 | D10: Дт | E10: 1 | F10: =IF($A10<>1,0,$E10*IF($D10="Дт",SUMIFS(ОСВ!$L$2:$L$5000,ОСВ!$J$2:$J$5000,$C10,ОСВ!$K$2:$K$5000,1),SUMIFS(ОСВ!$M$2:$M$5000,ОСВ!$J$2:$J$5000,$C10,ОСВ!$K$2:$K$5000,1))) -> 0 | G10: =IF($A10<>1,0,$E10*IF($D10="Дт",SUMIFS(ОСВ!$P$2:$P$5000,ОСВ!$J$2:$J$5000,$C10,ОСВ!$K$2:$K$5000,1),SUMIFS(ОСВ!$Q$2:$Q$5000,ОСВ!$J$2:$J$5000,$C10,ОСВ!$K$2:$K$5000,1))) -> 0
A11: 1 | B11: Деньги | C11: 55 | D11: Дт | E11: 1 | F11: =IF($A11<>1,0,$E11*IF($D11="Дт",SUMIFS(ОСВ!$L$2:$L$5000,ОСВ!$J$2:$J$5000,$C11,ОСВ!$K$2:$K$5000,1),SUMIFS(ОСВ!$M$2:$M$5000,ОСВ!$J$2:$J$5000,$C11,ОСВ!$K$2:$K$5000,1))) -> 0 | G11: =IF($A11<>1,0,$E11*IF($D11="Дт",SUMIFS(ОСВ!$P$2:$P$5000,ОСВ!$J$2:$J$5000,$C11,ОСВ!$K$2:$K$5000,1),SUMIFS(ОСВ!$Q$2:$Q$5000,ОСВ!$J$2:$J$5000,$C11,ОСВ!$K$2:$K$5000,1))) -> 0
A12: 1 | B12: Деньги | C12: 57 | D12: Дт | E12: 1 | F12: =IF($A12<>1,0,$E12*IF($D12="Дт",SUMIFS(ОСВ!$L$2:$L$5000,ОСВ!$J$2:$J$5000,$C12,ОСВ!$K$2:$K$5000,1),SUMIFS(ОСВ!$M$2:$M$5000,ОСВ!$J$2:$J$5000,$C12,ОСВ!$K$2:$K$5000,1))) -> 0 | G12: =IF($A12<>1,0,$E12*IF($D12="Дт",SUMIFS(ОСВ!$P$2:$P$5000,ОСВ!$J$2:$J$5000,$C12,ОСВ!$K$2:$K$5000,1),SUMIFS(ОСВ!$Q$2:$Q$5000,ОСВ!$J$2:$J$5000,$C12,ОСВ!$K$2:$K$5000,1))) -> 0
A13: 1 | B13: Финансовые вложения | C13: 58 | D13: Дт | E13: 1 | F13: =IF($A13<>1,0,$E13*IF($D13="Дт",SUMIFS(ОСВ!$L$2:$L$5000,ОСВ!$J$2:$J$5000,$C13,ОСВ!$K$2:$K$5000,1),SUMIFS(ОСВ!$M$2:$M$5000,ОСВ!$J$2:$J$5000,$C13,ОСВ!$K$2:$K$5000,1))) -> 0 | G13: =IF($A13<>1,0,$E13*IF($D13="Дт",SUMIFS(ОСВ!$P$2:$P$5000,ОСВ!$J$2:$J$5000,$C13,ОСВ!$K$2:$K$5000,1),SUMIFS(ОСВ!$Q$2:$Q$5000,ОСВ!$J$2:$J$5000,$C13,ОСВ!$K$2:$K$5000,1))) -> 0
A14: 1 | B14: Запасы | C14: 10 | D14: Дт | E14: 1 | F14: =IF($A14<>1,0,$E14*IF($D14="Дт",SUMIFS(ОСВ!$L$2:$L$5000,ОСВ!$J$2:$J$5000,$C14,ОСВ!$K$2:$K$5000,1),SUMIFS(ОСВ!$M$2:$M$5000,ОСВ!$J$2:$J$5000,$C14,ОСВ!$K$2:$K$5000,1))) -> 0 | G14: =IF($A14<>1,0,$E14*IF($D14="Дт",SUMIFS(ОСВ!$P$2:$P$5000,ОСВ!$J$2:$J$5000,$C14,ОСВ!$K$2:$K$5000,1),SUMIFS(ОСВ!$Q$2:$Q$5000,ОСВ!$J$2:$J$5000,$C14,ОСВ!$K$2:$K$5000,1))) -> 0
A15: 1 | B15: Запасы | C15: 41 | D15: Дт | E15: 1 | F15: =IF($A15<>1,0,$E15*IF($D15="Дт",SUMIFS(ОСВ!$L$2:$L$5000,ОСВ!$J$2:$J$5000,$C15,ОСВ!$K$2:$K$5000,1),SUMIFS(ОСВ!$M$2:$M$5000,ОСВ!$J$2:$J$5000,$C15,ОСВ!$K$2:$K$5000,1))) -> 0 | G15: =IF($A15<>1,0,$E15*IF($D15="Дт",SUMIFS(ОСВ!$P$2:$P$5000,ОСВ!$J$2:$J$5000,$C15,ОСВ!$K$2:$K$5000,1),SUMIFS(ОСВ!$Q$2:$Q$5000,ОСВ!$J$2:$J$5000,$C15,ОСВ!$K$2:$K$5000,1))) -> 0
A16: 1 | B16: Запасы | C16: 43 | D16: Дт | E16: 1 | F16: =IF($A16<>1,0,$E16*IF($D16="Дт",SUMIFS(ОСВ!$L$2:$L$5000,ОСВ!$J$2:$J$5000,$C16,ОСВ!$K$2:$K$5000,1),SUMIFS(ОСВ!$M$2:$M$5000,ОСВ!$J$2:$J$5000,$C16,ОСВ!$K$2:$K$5000,1))) -> 0 | G16: =IF($A16<>1,0,$E16*IF($D16="Дт",SUMIFS(ОСВ!$P$2:$P$5000,ОСВ!$J$2:$J$5000,$C16,ОСВ!$K$2:$K$5000,1),SUMIFS(ОСВ!$Q$2:$Q$5000,ОСВ!$J$2:$J$5000,$C16,ОСВ!$K$2:$K$5000,1))) -> 0
A17: 1 | B17: ДЗ | C17: 60.02 | D17: Дт | E17: 1 | F17: =IF($A17<>1,0,$E17*IF($D17="Дт",SUMIFS(ОСВ!$L$2:$L$5000,ОСВ!$J$2:$J$5000,$C17,ОСВ!$K$2:$K$5000,1),SUMIFS(ОСВ!$M$2:$M$5000,ОСВ!$J$2:$J$5000,$C17,ОСВ!$K$2:$K$5000,1))) -> 0 | G17: =IF($A17<>1,0,$E17*IF($D17="Дт",SUMIFS(ОСВ!$P$2:$P$5000,ОСВ!$J$2:$J$5000,$C17,ОСВ!$K$2:$K$5000,1),SUMIFS(ОСВ!$Q$2:$Q$5000,ОСВ!$J$2:$J$5000,$C17,ОСВ!$K$2:$K$5000,1))) -> 0
A18: 1 | B18: ДЗ | C18: 62.01 | D18: Дт | E18: 1 | F18: =IF($A18<>1,0,$E18*IF($D18="Дт",SUMIFS(ОСВ!$L$2:$L$5000,ОСВ!$J$2:$J$5000,$C18,ОСВ!$K$2:$K$5000,1),SUMIFS(ОСВ!$M$2:$M$5000,ОСВ!$J$2:$J$5000,$C18,ОСВ!$K$2:$K$5000,1))) -> 0 | G18: =IF($A18<>1,0,$E18*IF($D18="Дт",SUMIFS(ОСВ!$P$2:$P$5000,ОСВ!$J$2:$J$5000,$C18,ОСВ!$K$2:$K$5000,1),SUMIFS(ОСВ!$Q$2:$Q$5000,ОСВ!$J$2:$J$5000,$C18,ОСВ!$K$2:$K$5000,1))) -> 0
A19: 1 | B19: ДЗ | C19: 76.09 | D19: Дт | E19: 1 | F19: =IF($A19<>1,0,$E19*IF($D19="Дт",SUMIFS(ОСВ!$L$2:$L$5000,ОСВ!$J$2:$J$5000,$C19,ОСВ!$K$2:$K$5000,1),SUMIFS(ОСВ!$M$2:$M$5000,ОСВ!$J$2:$J$5000,$C19,ОСВ!$K$2:$K$5000,1))) -> 0 | G19: =IF($A19<>1,0,$E19*IF($D19="Дт",SUMIFS(ОСВ!$P$2:$P$5000,ОСВ!$J$2:$J$5000,$C19,ОСВ!$K$2:$K$5000,1),SUMIFS(ОСВ!$Q$2:$Q$5000,ОСВ!$J$2:$J$5000,$C19,ОСВ!$K$2:$K$5000,1))) -> 0
... A32: 1 | B32: Нераспределенная прибыль | C32: 84 | D32: Кт | E32: 1 | F32: =IF($A32<>1,0,$E32*IF($D32="Дт",SUMIFS(ОСВ!$L$2:$L$5000,ОСВ!$J$2:$J$5000,$C32,ОСВ!$K$2:$K$5000,1),SUMIFS(ОСВ!$M$2:$M$5000,ОСВ!$J$2:$J$5000,$C32,ОСВ!$K$2:$K$5000,1))) -> 0 | G32: =IF($A32<>1,0,$E32*IF($D32="Дт",SUMIFS(ОСВ!$P$2:$P$5000,ОСВ!$J$2:$J$5000,$C32,ОСВ!$K$2:$K$5000,1),SUMIFS(ОСВ!$Q$2:$Q$5000,ОСВ!$J$2:$J$5000,$C32,ОСВ!$K$2:$K$5000,1))) -> 0

Sheet P_l
B1: P_l | C1: Сумма
B2: Выручка | C2: =SUMIFS(Маппинг_PL!$F:$F,Маппинг_PL!$B:$B,B2) -> 0
B3: Себестоимость | C3: =SUMIFS(Маппинг_PL!$F:$F,Маппинг_PL!$B:$B,B3) -> 0
B4: Коммерческие расходы | C4: =SUMIFS(Маппинг_PL!$F:$F,Маппинг_PL!$B:$B,B4) -> 0
B5: Общехозяйственные расходы | C5: =SUMIFS(Маппинг_PL!$F:$F,Маппинг_PL!$B:$B,B5) -> 0
B6: Прочие доходы | C6: =SUMIFS(Маппинг_PL!$F:$F,Маппинг_PL!$B:$B,B6) -> 0
B7: Прочие расходы | C7: =SUMIFS(Маппинг_PL!$F:$F,Маппинг_PL!$B:$B,B7) -> 0
B8: Налог на прибыль | C8: =SUMIFS(Маппинг_PL!$F:$F,Маппинг_PL!$B:$B,B8) -> 0
B9: Финансовый результат | C9: =SUM(C2:C8) -> 0

Sheet BS
B1: BS | C1: Начало | D1: Конец
B2: Деньги | C2: =SUMIFS(Маппинг_BS!$F:$F,Маппинг_BS!$B:$B,B2) -> 0 | D2: =SUMIFS(Маппинг_BS!$G:$G,Маппинг_BS!$B:$B,B2) -> 0
B3: Финансовые вложения | C3: =SUMIFS(Маппинг_BS!$F:$F,Маппинг_BS!$B:$B,B3) -> 0 | D3: =SUMIFS(Маппинг_BS!$G:$G,Маппинг_BS!$B:$B,B3) -> 0
B4: Запасы | C4: =SUMIFS(Маппинг_BS!$F:$F,Маппинг_BS!$B:$B,B4) -> 0 | D4: =SUMIFS(Маппинг_BS!$G:$G,Маппинг_BS!$B:$B,B4) -> 0
B5: ДЗ | C5: =SUMIFS(Маппинг_BS!$F:$F,Маппинг_BS!$B:$B,B5) -> 0 | D5: =SUMIFS(Маппинг_BS!$G:$G,Маппинг_BS!$B:$B,B5) -> 0
B6: Оборотные активы | C6: =SUM(C2:C5) -> 0 | D6: =SUM(D2:D5) -> 0
B7: Основные средства | C7: =SUMIFS(Маппинг_BS!$F:$F,Маппинг_BS!$B:$B,B7) -> 0 | D7: =SUMIFS(Маппинг_BS!$G:$G,Маппинг_BS!$B:$B,B7) -> 0
B8: Активы всего | C8: =C6+C7 -> 0 | D8: =D6+D7 -> 0
B9: КЗ | C9: =SUMIFS(Маппинг_BS!$F:$F,Маппинг_BS!$B:$B,B9) -> 0 | D9: =SUMIFS(Маппинг_BS!$G:$G,Маппинг_BS!$B:$B,B9) -> 0
B10: Кредиты и займы | C10: =SUMIFS(Маппинг_BS!$F:$F,Маппинг_BS!$B:$B,B10) -> 0 | D10: =SUMIFS(Маппинг_BS!$G:$G,Маппинг_BS!$B:$B,B10) -> 0
B11: Налоги и взносы | C11: =SUMIFS(Маппинг_BS!$F:$F,Маппинг_BS!$B:$B,B11) -> 0 | D11: =SUMIFS(Маппинг_BS!$G:$G,Маппинг_BS!$B:$B,B11) -> 0
B12: Зарплата | C12: =SUMIFS(Маппинг_BS!$F:$F,Маппинг_BS!$B:$B,B12) -> 0 | D12: =SUMIFS(Маппинг_BS!$G:$G,Маппинг_BS!$B:$B,B12) -> 0
B13: Счетable persons | C13: =SUMIFS(Маппинг_BS!$F:$F,Маппинг_BS!$B:$B,B13) -> 0 | D13: =SUMIFS(Маппинг_BS!$G:$G,Маппинг_BS!$B:$B,B13) -> 0
B14: Краткосрочные обязательства | C14: =SUM(C9:C13) -> 0 | D14: =SUM(D9:D13) -> 0
B15: Капитал | C15: =SUMIFS(Маппинг_BS!$F:$F,Маппинг_BS!$B:$B,B15) -> 0 | D15: =SUMIFS(Маппинг_BS!$G:$G,Маппинг_BS!$B:$B,B15) -> 0
B16: Нераспределенная прибыль | C16: =SUMIFS(Маппинг_BS!$F:$F,Маппинг_BS!$B:$B,B16) -> 0 | D16: =SUMIFS(Маппинг_BS!$G:$G,Маппинг_BS!$B:$B,B16) -> 0
B17: Пассивы всего | C17: =SUM(C14:C16) -> 0 | D17: =SUM(D14:D16) -> 0
B18: Чистый оборотный капитал | C18: =C6-C14 -> 0 | D18: =D6-D14 -> 0
B19: Стоимость компании | C19: =C2+C3+C5+C7-C9-C10-C11-C12 -> 0 | D19: =D2+D3+D5+D7-D9-D10-D11-D12 -> 0
